descartes/__init__.py
descartes/descartes.py
descartes/utils.py
decare-0.0.1.dist-info/LICENSE
decare-0.0.1.dist-info/METADATA
decare-0.0.1.dist-info/WHEEL
decare-0.0.1.dist-info/top_level.txt
decare-0.0.1.dist-info/RECORD
