Metadata-Version: 2.1
Name: decare
Version: 0.0.1
Summary: Detection of spatial chromatin accessibility patterns with inter-cellular correlations
Home-page: https://github.com/likeyi19/Descartes
Author: Likeyi
Author-email: lky23@mails.tsinghua.edu.cn
License: MIT
License-File: LICENSE
Requires-Dist: anndata (>=0.9.2)
Requires-Dist: matplotlib (>=3.7.4)
Requires-Dist: numpy (>=1.22.4)
Requires-Dist: pandas (>=1.4.3)
Requires-Dist: scanpy (==1.9.6)
Requires-Dist: scikit-learn (>=1.3.0)
Requires-Dist: scipy (>=1.8.0)
Requires-Dist: seaborn (>=0.12.2)
